subcaretin/__init__.py
subcaretin/filtros.py
subcaretin/guess.py
subcaretin/mejor_sub.py
subcaretin/providers.py
subcaretin-0.3.3.data/scripts/subcaretin
subcaretin-0.3.3.dist-info/LICENSE
subcaretin-0.3.3.dist-info/METADATA
subcaretin-0.3.3.dist-info/WHEEL
subcaretin-0.3.3.dist-info/top_level.txt
subcaretin-0.3.3.dist-info/RECORD
