Metadata-Version: 2.1
Name: subcaretin
Version: 0.3.3
Summary: Descarga automática de subtítulos desde Argenteam y Subdivx
Home-page: https://github.com/vitiko123/subcaretin
Author: Vitiko
Author-email: vhnz98@gmail.com
License: UNKNOWN
Platform: UNKNOWN
Classifier: Programming Language :: Python :: 3
Classifier: License :: OSI Approved :: GNU General Public License (GPL)
Classifier: Operating System :: OS Independent
Requires-Python: >=3.6
Requires-Dist: requests
Requires-Dist: guessit
Requires-Dist: beautifulsoup4
Requires-Dist: python-magic
Requires-Dist: unrar
